bkkcsirip.py
bkkcsirip-1.1.0.dist-info/DESCRIPTION.rst
bkkcsirip-1.1.0.dist-info/METADATA
bkkcsirip-1.1.0.dist-info/RECORD
bkkcsirip-1.1.0.dist-info/WHEEL
bkkcsirip-1.1.0.dist-info/metadata.json
bkkcsirip-1.1.0.dist-info/top_level.txt
