Metadata-Version: 2.0
Name: bkkcsirip
Version: 1.1.0
Summary: UNKNOWN
Home-page: https://github.com/underyx/bkkcsirip
Author: Bence Nagy
Author-email: bence@underyx.me
License: UNKNOWN
Download-URL: https://github.com/underyx/bkkcsirip/releases
Platform: UNKNOWN
Classifier: Development Status :: 5 - Production/Stable
Classifier: Environment :: Console
Classifier: License :: OSI Approved :: MIT License
Classifier: Operating System :: OS Independent
Classifier: Programming Language :: Python
Classifier: Programming Language :: Python :: 2
Classifier: Programming Language :: Python :: 2.7
Classifier: Programming Language :: Python :: 3
Classifier: Programming Language :: Python :: 3.4
Requires-Dist: arrow (<0.9)
Requires-Dist: oauthlib (<2)
Requires-Dist: redis (<3)
Requires-Dist: requests (<3)
Requires-Dist: requests-oauthlib (<0.6)
